jourgen/__init__.py
jourgen/__main__.py
jourgen/jourgen.py
jourgen/manage.py
jourgen/settings.py
jourgen/__pycache__/jourgen.cpython-38.pyc
jourgen/__pycache__/settings.cpython-38.pyc
jourgen/pages/about.md
jourgen/posts/2020-05-25-bugs.md
jourgen/posts/2020-05-31-contribute.md
jourgen/posts/2020-06-01-publish-post.md
jourgen/posts/2020-06-05-customize-journal.md
jourgen/posts/2020-06-06-write-your-journal.md
jourgen/posts/2020-06-10-getting-started.md
jourgen/posts/2020-06-11-welcome.md
jourgen/posts/2020-08-21-creating-a-blog.md
jourgen/posts/2020-08-22-creating-a-blog-engine.md
jourgen/posts/2020-08-25-creating-an-engine.md
jourgen/static/base.css
jourgen/static/base.js
jourgen/static/code.css
jourgen/static/content.css
jourgen/static/footer.css
jourgen/static/forest-inv.css
jourgen/static/forest.css
jourgen/static/glacier-inv.css
jourgen/static/glacier.css
jourgen/static/guanaco.jpg
jourgen/static/header.css
jourgen/static/lemonbar.css
jourgen/static/mobile.css
jourgen/static/pinguino.jpg
jourgen/static/post.css
jourgen/templates/about.html
jourgen/templates/base.html
jourgen/templates/footer.html
jourgen/templates/header.html
jourgen/templates/index.html
jourgen/templates/page.html
jourgen/templates/post.html
jourgen-0.0.10.4.dist-info/LICENSE.txt
jourgen-0.0.10.4.dist-info/METADATA
jourgen-0.0.10.4.dist-info/WHEEL
jourgen-0.0.10.4.dist-info/entry_points.txt
jourgen-0.0.10.4.dist-info/top_level.txt
jourgen-0.0.10.4.dist-info/RECORD
